aeon/__init__.py
aeon/util.py
aeon/analysis/__init__.py
aeon/analysis/movies.py
aeon/analysis/plotting.py
aeon/analysis/utils.py
aeon/io/__init__.py
aeon/io/api.py
aeon/io/device.py
aeon/io/reader.py
aeon/io/video.py
aeon/schema/__init__.py
aeon/schema/core.py
aeon/schema/streams.py
swc_aeon-0.1.0.dist-info/METADATA
swc_aeon-0.1.0.dist-info/WHEEL
swc_aeon-0.1.0.dist-info/license.md
swc_aeon-0.1.0.dist-info/top_level.txt
swc_aeon-0.1.0.dist-info/RECORD
