Metadata-Version: 2.2
Name: swc-aeon
Version: 0.1.0
Summary: A package for interfacing with acquired data from Project Aeon experiments.
Author-email: Jai Bhagat <jkbhagatio@gmail.com>, Goncalo Lopes <g.lopes@neurogears.org>, Thinh Nguyen <thinh@datajoint.com>, Chang Huan Lo <changhuan.lo@ucl.ac.uk>, Joseph Burling <joseph@datajoint.com>, Jaerong Ahn <jaerong.ahn@datajoint.com>, Milagros Marin <milagros@datajoint.com>
License: BSD 3-Clause License
Project-URL: Homepage, https://sainsburywellcomecentre.github.io/aeon_docs/
Project-URL: Repository, https://github.com/sainsburyWellcomeCentre/aeon_api
Project-URL: Documentation, https://sainsburywellcomecentre.github.io/aeon_docs/
Requires-Python: >=3.11
License-File: license.md
Requires-Dist: dotmap
Requires-Dist: matplotlib
Requires-Dist: numpy<2,>=1.21.0
Requires-Dist: opencv-python
Requires-Dist: pandas>=1.3
Provides-Extra: dev
Requires-Dist: pre-commit; extra == "dev"
Requires-Dist: pyright; extra == "dev"
Requires-Dist: pytest; extra == "dev"
Requires-Dist: pytest-cov; extra == "dev"
Requires-Dist: ruff; extra == "dev"
